lrgs/__init__.py
lrgs/lrgs.py
lrgs/trunc.py
lrgs-0.1.1.dist-info/LICENSE
lrgs-0.1.1.dist-info/METADATA
lrgs-0.1.1.dist-info/WHEEL
lrgs-0.1.1.dist-info/top_level.txt
lrgs-0.1.1.dist-info/RECORD
