Metadata-Version: 2.1
Name: lrgs
Version: 0.1.1
Summary: Linear Regression by Gibbs Sampling
Home-page: https://github.com/abmantz/lrgs
Author: Adam Mantz
Author-email: amantz@slac.stanford.edu
License: MIT
Platform: UNKNOWN
Classifier: Development Status :: 3 - Alpha
Classifier: Intended Audience :: Science/Research
Classifier: License :: OSI Approved :: MIT License
Classifier: Programming Language :: Python :: 2
Classifier: Programming Language :: Python :: 2.7
Requires-Dist: numpy
Requires-Dist: scipy
